crowbar/__init__.py
crowbar/crowbar.py
crowbar/main.py
crowbar_package_manager-0.1.16.dist-info/METADATA
crowbar_package_manager-0.1.16.dist-info/WHEEL
crowbar_package_manager-0.1.16.dist-info/entry_points.txt
crowbar_package_manager-0.1.16.dist-info/top_level.txt
crowbar_package_manager-0.1.16.dist-info/RECORD
