Metadata-Version: 2.1
Name: crowbar-package-manager
Version: 0.1.16
Summary: a local-first tool for managing python dependencies with pip
Requires-Dist: toml
Requires-Dist: appdirs
